deva/__init__.py
deva/admin.py
deva/browser.py
deva/bus.py
deva/compute.py
deva/core.py
deva/endpoints.py
deva/future.py
deva/gpt.py
deva/graph.py
deva/lambdas.py
deva/monitor.py
deva/namespace.py
deva/page.py
deva/pipe.py
deva/search.py
deva/sources.py
deva/store.py
deva/topic.py
deva/when.py
deva/utils/__init__.py
deva/utils/simhash.py
deva/utils/sqlitedict.py
deva/utils/time.py
deva/utils/whooshalchemy.py
deva-1.3.2.dist-info/METADATA
deva-1.3.2.dist-info/WHEEL
deva-1.3.2.dist-info/top_level.txt
deva-1.3.2.dist-info/RECORD
