Metadata-Version: 2.1
Name: deva
Version: 1.3.2
Summary: data eval in future
Home-page: https://github.com/sostc/deva
Author: spark
Author-email: zjw0358@gmail.com
License: http://www.apache.org/licenses/LICENSE-2.0.html
Requires-Python: >=3.5
Requires-Dist: toolz
Requires-Dist: zict
Requires-Dist: jieba
Requires-Dist: six
Requires-Dist: requests
Requires-Dist: pandas
Requires-Dist: pandas-compat
Requires-Dist: dill
Requires-Dist: Whoosh
Requires-Dist: SQLAlchemy
Requires-Dist: tornado
Requires-Dist: easyquotation
Requires-Dist: pampy
Requires-Dist: pymaybe
Requires-Dist: requests-html
Requires-Dist: aioredis>=2.0
Requires-Dist: apscheduler
Requires-Dist: werkzeug==1.0.0
Requires-Dist: networkx==2
Requires-Dist: graphviz
Requires-Dist: sockjs-tornado>=1.0.7
Requires-Dist: expiringdict
Requires-Dist: aiosmtplib
Requires-Dist: trafilatura
Requires-Dist: newspaper3k
Requires-Dist: boilerpy3
Requires-Dist: sumy
